[{"line":1,"elements":[{"line":2,"name":"","description":"","type":"background","keyword":"Background","steps":[{"result":{"error_message":"java.lang.AssertionError: 1 expectation failed.\nExpected status code <200> but was <302>.\n\r\n\tat java.base/jdk.internal.reflect.NativeConstructorAccessorImpl.newInstance0(Native Method)\r\n\tat java.base/jdk.internal.reflect.NativeConstructorAccessorImpl.newInstance(NativeConstructorAccessorImpl.java:62)\r\n\tat java.base/jdk.internal.reflect.DelegatingConstructorAccessorImpl.newInstance(DelegatingConstructorAccessorImpl.java:45)\r\n\tat java.base/java.lang.reflect.Constructor.newInstance(Constructor.java:490)\r\n\tat org.codehaus.groovy.reflection.CachedConstructor.invoke(CachedConstructor.java:73)\r\n\tat org.codehaus.groovy.reflection.CachedConstructor.doConstructorInvoke(CachedConstructor.java:60)\r\n\tat org.codehaus.groovy.runtime.callsite.ConstructorSite$ConstructorSiteNoUnwrap.callConstructor(ConstructorSite.java:86)\r\n\tat org.codehaus.groovy.runtime.callsite.CallSiteArray.defaultCallConstructor(CallSiteArray.java:57)\r\n\tat org.codehaus.groovy.runtime.callsite.AbstractCallSite.callConstructor(AbstractCallSite.java:263)\r\n\tat org.codehaus.groovy.runtime.callsite.AbstractCallSite.callConstructor(AbstractCallSite.java:277)\r\n\tat io.restassured.internal.ResponseSpecificationImpl$HamcrestAssertionClosure.validate(ResponseSpecificationImpl.groovy:512)\r\n\tat io.restassured.internal.ResponseSpecificationImpl$HamcrestAssertionClosure$validate$1.call(Unknown Source)\r\n\tat org.codehaus.groovy.runtime.callsite.CallSiteArray.defaultCall(CallSiteArray.java:45)\r\n\tat org.codehaus.groovy.runtime.callsite.AbstractCallSite.call(AbstractCallSite.java:125)\r\n\tat org.codehaus.groovy.runtime.callsite.AbstractCallSite.call(AbstractCallSite.java:139)\r\n\tat io.restassured.internal.ResponseSpecificationImpl.validateResponseIfRequired(ResponseSpecificationImpl.groovy:696)\r\n\tat io.restassured.internal.ResponseSpecificationImpl.this$2$validateResponseIfRequired(ResponseSpecificationImpl.groovy)\r\n\tat java.base/jdk.internal.reflect.NativeMethodAccessorImpl.invoke0(Native Method)\r\n\tat java.base/jdk.internal.reflect.NativeMethodAccessorImpl.invoke(NativeMethodAccessorImpl.java:62)\r\n\tat java.base/jdk.internal.reflect.DelegatingMethodAccessorImpl.invoke(DelegatingMethodAccessorImpl.java:43)\r\n\tat java.base/java.lang.reflect.Method.invoke(Method.java:566)\r\n\tat org.codehaus.groovy.runtime.callsite.PlainObjectMetaMethodSite.doInvoke(PlainObjectMetaMethodSite.java:43)\r\n\tat org.codehaus.groovy.runtime.callsite.PogoMetaMethodSite$PogoCachedMethodSiteNoUnwrapNoCoerce.invoke(PogoMetaMethodSite.java:198)\r\n\tat org.codehaus.groovy.runtime.callsite.PogoMetaMethodSite.callCurrent(PogoMetaMethodSite.java:62)\r\n\tat org.codehaus.groovy.runtime.callsite.CallSiteArray.defaultCallCurrent(CallSiteArray.java:49)\r\n\tat org.codehaus.groovy.runtime.callsite.AbstractCallSite.callCurrent(AbstractCallSite.java:171)\r\n\tat org.codehaus.groovy.runtime.callsite.AbstractCallSite.callCurrent(AbstractCallSite.java:185)\r\n\tat io.restassured.internal.ResponseSpecificationImpl.statusCode(ResponseSpecificationImpl.groovy:135)\r\n\tat io.restassured.specification.ResponseSpecification$statusCode$0.callCurrent(Unknown Source)\r\n\tat org.codehaus.groovy.runtime.callsite.CallSiteArray.defaultCallCurrent(CallSiteArray.java:49)\r\n\tat org.codehaus.groovy.runtime.callsite.AbstractCallSite.callCurrent(AbstractCallSite.java:171)\r\n\tat org.codehaus.groovy.runtime.callsite.AbstractCallSite.callCurrent(AbstractCallSite.java:185)\r\n\tat io.restassured.internal.ResponseSpecificationImpl.statusCode(ResponseSpecificationImpl.groovy:143)\r\n\tat io.restassured.internal.ValidatableResponseOptionsImpl.statusCode(ValidatableResponseOptionsImpl.java:89)\r\n\tat APISteps.APIStepsClass.a_jwt_bearer_token_is_generated(APIStepsClass.java:41)\r\n\tat ✽.a JWT bearer token is generated(file:///C:/Users/wmina/Desktop/UdemyProject/HRMSBatch19/src/test/resources/feature/APIWorkflow.feature:3)\r\n","duration":1191861600,"status":"failed"},"line":3,"name":"a JWT bearer token is generated","match":{"location":"APISteps.APIStepsClass.a_jwt_bearer_token_is_generated()"},"keyword":"Given "}]},{"start_timestamp":"2024-07-10T01:13:10.420Z","line":25,"name":"Create employee using json payload","description":"","id":"api-testing;create-employee-using-json-payload","type":"scenario","keyword":"Scenario","steps":[{"result":{"status":"skipped"},"line":26,"name":"a request is prepared for creating an employee using json payload","match":{"location":"APISteps.APIStepsClass.a_request_is_prepared_for_creating_an_employee_using_json_payload()"},"keyword":"Given "},{"result":{"status":"skipped"},"line":27,"name":"a POST call is made to create the employee","match":{"location":"APISteps.APIStepsClass.a_post_call_is_made_to_create_the_employee()"},"keyword":"When "},{"result":{"duration":1070900,"status":"skipped"},"line":28,"name":"the status code will be 201 for this call","match":{"arguments":[{"val":"201","offset":24}],"location":"APISteps.APIStepsClass.the_status_code_will_be_for_this_call(java.lang.Integer)"},"keyword":"Then "},{"result":{"status":"skipped"},"line":29,"name":"the employee created contains key \"Message\" and value \"Employee Created\"","match":{"arguments":[{"val":"\"Message\"","offset":34},{"val":"\"Employee Created\"","offset":54}],"location":"APISteps.APIStepsClass.the_employee_created_contains_key_and_value(java.lang.String,java.lang.String)"},"keyword":"And "},{"result":{"status":"skipped"},"line":30,"name":"the employee id \"Employee.employee_id\" is stored as a global variable","match":{"arguments":[{"val":"\"Employee.employee_id\"","offset":16}],"location":"APISteps.APIStepsClass.the_employee_id_is_stored_as_a_global_variable(java.lang.String)"},"keyword":"And "}],"tags":[{"name":"@jsonpayload"}]}],"name":"API testing","description":"","id":"api-testing","keyword":"Feature","uri":"file:src/test/resources/feature/APIWorkflow.feature","tags":[]}]